humblematch/runtests.py
humblematch/wrap_obj.py
humblematch/__init__.py
humblematch-0.1.1.dist-info/DESCRIPTION.rst
humblematch-0.1.1.dist-info/METADATA
humblematch-0.1.1.dist-info/metadata.json
humblematch-0.1.1.dist-info/pbr.json
humblematch-0.1.1.dist-info/RECORD
humblematch-0.1.1.dist-info/top_level.txt
humblematch-0.1.1.dist-info/WHEEL
