Metadata-Version: 2.0
Name: humblematch
Version: 0.1.1
Summary: Will Sanitize your type-checks and duck-checks for you
Home-page: https://github.com/bendtherules/humblematch
Author: bendtherules
Author-email: bendtherules@codesp.in
License: WTFPL
Download-URL: https://github.com/bendtherules/humblematch/tarball/0.1.dev3
Keywords: type-checking,testing,assert
Platform: UNKNOWN
Classifier: Development Status :: 3 - Alpha
